speedtest.py
speedtest_cli.py
speedtest_cli-2.1.1.dist-info/METADATA
speedtest_cli-2.1.1.dist-info/RECORD
speedtest_cli-2.1.1.dist-info/WHEEL
speedtest_cli-2.1.1.dist-info/entry_points.txt
speedtest_cli-2.1.1.dist-info/top_level.txt
